looter/__init__.py
looter/templates/data.tmpl
looter/templates/data_async.tmpl
looter-2.21.dist-info/LICENSE
looter-2.21.dist-info/METADATA
looter-2.21.dist-info/WHEEL
looter-2.21.dist-info/entry_points.txt
looter-2.21.dist-info/top_level.txt
looter-2.21.dist-info/RECORD
