Metadata-Version: 2.1
Name: looter
Version: 2.21
Summary: A python package aiming at avoiding unnecessary repetition in making common crawlers.
Home-page: https://github.com/alphardex/looter
Author: alphardex
Author-email: 2582347430@qq.com
License: MIT
Platform: all
Classifier: Development Status :: 3 - Alpha
Classifier: Environment :: Console
Classifier: Intended Audience :: Developers
Classifier: Intended Audience :: End Users/Desktop
Classifier: License :: OSI Approved :: MIT License
Classifier: Programming Language :: Python :: 3.6
Classifier: Topic :: Internet
Classifier: Topic :: Internet :: WWW/HTTP
Classifier: Topic :: Utilities
Requires-Python: >=3.6.0
Requires-Dist: requests
Requires-Dist: docopt
Requires-Dist: parsel
Requires-Dist: aiohttp
Requires-Dist: tqdm
